karabo_data/__init__.py
karabo_data/components.py
karabo_data/exceptions.py
karabo_data/export.py
karabo_data/geometry.py
karabo_data/h5index.py
karabo_data/lsxfel.py
karabo_data/read_machinery.py
karabo_data/reader.py
karabo_data/run_files_map.py
karabo_data/stacking.py
karabo_data/utils.py
karabo_data/validation.py
karabo_data/write_cxi.py
karabo_data/writer.py
karabo_data/cli/__init__.py
karabo_data/cli/make_virtual_cxi.py
karabo_data/geometry2/__init__.py
karabo_data/geometry2/crystfel_fmt.py
karabo_data/tests/__init__.py
karabo_data/tests/conftest.py
karabo_data/tests/dssc_geo_june19.h5
karabo_data/tests/lpd_mar_18.h5
karabo_data/tests/make_examples.py
karabo_data/tests/test_agipd_geometry.py
karabo_data/tests/test_components.py
karabo_data/tests/test_dssc_geometry.py
karabo_data/tests/test_geometry_old.py
karabo_data/tests/test_lpd_geometry.py
karabo_data/tests/test_lsxfel.py
karabo_data/tests/test_read_machinery.py
karabo_data/tests/test_reader_mockdata.py
karabo_data/tests/test_run_files_map.py
karabo_data/tests/test_slice_objs.py
karabo_data/tests/test_stacking.py
karabo_data/tests/test_streamer.py
karabo_data/tests/test_utils.py
karabo_data/tests/test_validation.py
karabo_data/tests/test_writer.py
karabo_data/tests/cli/__init__.py
karabo_data/tests/cli/test_make_virtual_cxi.py
karabo_data/tests/mockdata/__init__.py
karabo_data/tests/mockdata/adc.py
karabo_data/tests/mockdata/base.py
karabo_data/tests/mockdata/basler_camera.py
karabo_data/tests/mockdata/control_common.py
karabo_data/tests/mockdata/dctrl.py
karabo_data/tests/mockdata/detectors.py
karabo_data/tests/mockdata/gauge.py
karabo_data/tests/mockdata/gec_camera.py
karabo_data/tests/mockdata/imgfel.py
karabo_data/tests/mockdata/mkfile.py
karabo_data/tests/mockdata/motor.py
karabo_data/tests/mockdata/mpod.py
karabo_data/tests/mockdata/sidemic_camera.py
karabo_data/tests/mockdata/tsens.py
karabo_data/tests/mockdata/uvlamp.py
karabo_data-0.7.0.dist-info/METADATA
karabo_data-0.7.0.dist-info/RECORD
karabo_data-0.7.0.dist-info/WHEEL
karabo_data-0.7.0.dist-info/entry_points.txt
karabo_data-0.7.0.dist-info/top_level.txt
