Metadata-Version: 2.1
Name: karabo-data
Version: 0.7.0
Summary: Tools to read and analyse data from European XFEL 
Home-page: https://github.com/European-XFEL/karabo_data
Author: European XFEL GmbH
Author-email: da-support@xfel.eu
Maintainer: Thomas Michelat
License: BSD-3-Clause
Platform: UNKNOWN
Classifier: Development Status :: 3 - Alpha
Classifier: Environment :: Console
Classifier: Intended Audience :: Developers
Classifier: Intended Audience :: Science/Research
Classifier: License :: OSI Approved :: BSD License
Classifier: Operating System :: POSIX :: Linux
Classifier: Programming Language :: Python :: 3
Classifier: Programming Language :: Python :: 3.5
Classifier: Programming Language :: Python :: 3.6
Classifier: Programming Language :: Python :: 3.7
Classifier: Topic :: Scientific/Engineering :: Information Analysis
Classifier: Topic :: Scientific/Engineering :: Physics
Requires-Python: >=3.5
Provides-Extra: docs
Provides-Extra: test
Requires-Dist: cfelpyutils (>=0.92)
Requires-Dist: fabio
Requires-Dist: h5py (>=2.7.1)
Requires-Dist: karabo-bridge
Requires-Dist: matplotlib
Requires-Dist: msgpack (>=0.5.4)
Requires-Dist: msgpack-numpy (>=0.4.3)
Requires-Dist: numpy
Requires-Dist: pandas
Requires-Dist: pyzmq (>=17.0.0)
Requires-Dist: scipy
Requires-Dist: xarray
Provides-Extra: docs
Requires-Dist: sphinx; extra == 'docs'
Requires-Dist: nbsphinx; extra == 'docs'
Requires-Dist: ipython; extra == 'docs'
Requires-Dist: sphinxcontrib-github-alt; extra == 'docs'
Provides-Extra: test
Requires-Dist: dask[array]; extra == 'test'
Requires-Dist: pytest; extra == 'test'
Requires-Dist: pytest-cov; extra == 'test'
Requires-Dist: nbval; extra == 'test'
Requires-Dist: testpath; extra == 'test'
